ek_data_structures/__init__.py
ek_data_structures/array.py
ek_data_structures/doubly_linked_list.py
ek_data_structures/graph.py
ek_data_structures/linked_list.py
ek_data_structures/queue.py
ek_data_structures/stack.py
ek_data_structures/tree.py
ek_data_structures-0.0.3.dist-info/LICENSE
ek_data_structures-0.0.3.dist-info/METADATA
ek_data_structures-0.0.3.dist-info/WHEEL
ek_data_structures-0.0.3.dist-info/top_level.txt
ek_data_structures-0.0.3.dist-info/RECORD
