Metadata-Version: 2.1
Name: ek-data-structures
Version: 0.0.3
Summary: A Python package that implements common data structures such as Array, Stack, Queue, Linked List, Binary Tree, and Graph.
Home-page: https://ekbarkacha.github.io/data-structure-package-documentation/
Author: Emmanuel Kirui Barkacha
Author-email: ebarkacha@aimsammi.org
Classifier: Programming Language :: Python :: 3
Classifier: License :: OSI Approved :: MIT License
Classifier: Operating System :: OS Independent
Requires-Python: >=3.6
License-File: LICENSE
